penelopa_dialog/__init__.py
penelopa_dialog/main_logic.py
penelopa_dialog-2025.5.160654.dist-info/licenses/LICENSE
penelopa_dialog-2025.5.160654.dist-info/METADATA
penelopa_dialog-2025.5.160654.dist-info/WHEEL
penelopa_dialog-2025.5.160654.dist-info/top_level.txt
penelopa_dialog-2025.5.160654.dist-info/RECORD
