Metadata-Version: 2.4
Name: penelopa-dialog
Version: 2025.5.160654
Summary: Penelopa Dialog for managing and coordinating tasks
Home-page: https://github.com/chigwell/penelopa-dialog
Author: Eugene Evstafev
Author-email: chigwel@gmail.com
Classifier: Development Status :: 3 - Alpha
Classifier: Intended Audience :: Developers
Classifier: License :: OSI Approved :: MIT License
Classifier: Programming Language :: Python :: 3
Requires-Python: >=3.6
License-File: LICENSE
Dynamic: author
Dynamic: author-email
Dynamic: classifier
Dynamic: description
Dynamic: description-content-type
Dynamic: home-page
Dynamic: license-file
Dynamic: requires-python
Dynamic: summary
